MultiResImagePy.cpython-311-darwin.so
multiresimage/lib/libCore.dylib
multiresimage/lib/libEncode.dylib
multiresimage/lib/libImage.dylib
multiresimage/lib/libImageBuffer.dylib
multiresimage/lib/libImageBufferIO.dylib
multiresimage/lib/libMultiResImage.dylib
multiresimage/lib/libPlacement.dylib
multiresimage/lib/libUtils.dylib
multiresimage/lib/libiXML.dylib
multiresimage/lib/liblibtiff.dylib
MultiResImagePy-0.2.dist-info/METADATA
MultiResImagePy-0.2.dist-info/WHEEL
MultiResImagePy-0.2.dist-info/top_level.txt
MultiResImagePy-0.2.dist-info/RECORD
